{"uniqueName":"/Lotus/Weapons/Syndicates/RedVeil/Pistols/RVBallistica","name":"Rakta Ballistica","displayClass":"Crossbow","modPools":["Rifle","Rakta Ballistica"],"polarities":["vazarin","madurai"],"exilusPolarity":"naramon","stancePolarity":null,"family":"Ballistica","slot":"Secondary","traits":["Syndicate","Red Veil"],"masteryReq":6,"productCategory":"Pistols","fireRate":3.3333335,"magazineSize":20,"reloadTime":2,"totalDamage":300,"damagePerShot":[15,270,15.000004,0,0,0,0,0,0,0,0,0,0,0,0,0,0,0,0,0],"criticalChance":0.050000001,"criticalMultiplier":1.5,"procChance":0.10000002,"accuracy":4,"multishot":1,"trigger":"CHARGE","attacks":[{"name":"Charged Shot","speed":3.33,"crit_chance":20,"crit_mult":1.5,"status_chance":10,"shot_type":"Projectile","trigger":"Charge","damage":{"impact":15,"puncture":270,"slash":15}},{"name":"Burst Shot","speed":6.67,"crit_chance":5,"crit_mult":1.5,"status_chance":5,"shot_type":"Projectile","trigger":"Burst","damage":{"impact":18.75,"puncture":37.5,"slash":18.75}}],"damage":{"impact":15,"puncture":270,"slash":15},"imageName":"https://img.arsenyx.com/RaktaBallistica-645f7348.png"}