{"uniqueName":"/Lotus/Weapons/Grineer/Pistols/GrnUzi/GrnUziWeapon","name":"Stubba","displayClass":"Pistol","modPools":["Pistol","Stubba","Pistol (No Aoe)","SECONDARY"],"polarities":[],"exilusPolarity":"madurai","stancePolarity":null,"family":"Stubba","slot":"Secondary","traits":["Grineer"],"masteryReq":7,"productCategory":"Pistols","omegaAttenuation":1.35,"fireRate":6.3333335,"magazineSize":57,"reloadTime":1.3,"totalDamage":33,"damagePerShot":[14.190001,3.3,15.509999,0,0,0,0,0,0,0,0,0,0,0,0,0,0,0,0,0],"criticalChance":0.23,"criticalMultiplier":1.9,"procChance":0.13,"accuracy":16,"multishot":1,"trigger":"AUTO","attacks":[{"name":"Normal Attack","speed":6.33,"crit_chance":23,"crit_mult":1.9,"status_chance":13,"shot_type":"Hit-Scan","range":300,"damage":{"impact":14.19,"puncture":3.3,"slash":15.51}}],"damage":{"impact":14.19,"puncture":3.3,"slash":15.51},"imageName":"https://img.arsenyx.com/Stubba-f0900bde.png"}