{"uniqueName":"/Lotus/Types/Sentinels/SentinelPowersuits/CarrierPowerSuit","name":"Carrier","subType":"sentinel","description":"With 'Assault Mode' and 'Ammo Case' as default Precepts, Carrier is a seeker Sentinel. Carrier also comes with a shotgun weapon.\r\n\r\nNote: This item requires two open slots.","health":560,"shield":250,"armor":80,"power":100,"masteryReq":0,"polarities":["penjaga","penjaga","penjaga","vazarin","penjaga"],"isPrime":false,"modPools":["COMPANION","Carrier","Sentinel","ROBOTIC"],"imageName":"https://img.arsenyx.com/Carrier-23b173bd.png"}