{"uniqueName":"/Lotus/Weapons/Sentients/SentOctaMiniGun/SentOctaMiniGun","name":"Haalvu","displayClass":"Rifle","modPools":["Rifle","Haalvu","Rifle (No Aoe)","PRIMARY"],"polarities":[],"exilusPolarity":null,"stancePolarity":null,"family":"Haalvu","slot":"Primary","traits":["Sentient"],"masteryReq":8,"productCategory":"LongGuns","omegaAttenuation":0.5,"fireRate":15.000001,"magazineSize":200,"reloadTime":13.833333,"totalDamage":90,"damagePerShot":[23.4,23.4,43.200001,0,0,0,0,0,0,0,0,0,0,0,0,0,0,0,0,0],"criticalChance":0.22,"criticalMultiplier":2.2,"procChance":0.22000003,"accuracy":100,"multishot":1,"trigger":"AUTO","attacks":[{"name":"Normal Attack","speed":15,"crit_chance":22,"crit_mult":2.2,"status_chance":22,"shot_type":"Hit-Scan","damage":{"impact":23.4,"puncture":23.4,"slash":43.2}}],"damage":{"impact":23.4,"puncture":23.4,"slash":43.2},"imageName":"https://img.arsenyx.com/TnoOctaMiniGun-c1c33db3.png"}