{"uniqueName":"/Lotus/Weapons/Infested/LongGuns/InfWFAccompanyingPri/InfestedBurstRifle","name":"Hema","displayClass":"Rifle","modPools":["Rifle","Hema","Rifle (No Aoe)"],"polarities":["madurai"],"exilusPolarity":"naramon","stancePolarity":null,"family":"Hema","slot":"Primary","traits":["Infested"],"masteryReq":7,"productCategory":"LongGuns","fireRate":6,"magazineSize":60,"reloadTime":2,"totalDamage":47,"damagePerShot":[0,0,0,0,0,0,0,0,0,0,0,47,0,0,0,0,0,0,0,0],"criticalChance":0.11,"criticalMultiplier":2,"procChance":0.25,"accuracy":20,"multishot":1,"trigger":"BURST","attacks":[{"name":"Normal Attack","speed":5,"crit_chance":11,"crit_mult":2,"status_chance":25,"shot_type":"Projectile","damage":{"viral":47}}],"damage":{"viral":47},"imageName":"https://img.arsenyx.com/Hema-e418d62c.png"}