{"uniqueName":"/Lotus/Weapons/Tenno/LongGuns/TnRailjackRifle/RailjackRifleGun","name":"Quellor","displayClass":"Rifle","modPools":["Rifle","Quellor","Rifle (No Aoe)","PRIMARY"],"polarities":["madurai","madurai"],"exilusPolarity":"madurai","stancePolarity":null,"family":"Quellor","slot":"Primary","traits":["Tenno"],"masteryReq":12,"productCategory":"LongGuns","omegaAttenuation":1.15,"fireRate":6.0000005,"magazineSize":300,"reloadTime":4,"totalDamage":58,"damagePerShot":[8,22,12,0,16,0,0,0,0,0,0,0,0,0,0,0,0,0,0,0],"criticalChance":0.12,"criticalMultiplier":1.6,"procChance":0.38,"accuracy":33.333332,"multishot":1,"trigger":"AUTO","attacks":[{"name":"Auto","speed":6,"crit_chance":12,"crit_mult":1.6,"status_chance":38,"shot_type":"Hit-Scan","range":300,"punch_through":0.5,"damage":{"cold":16,"impact":8,"puncture":22,"slash":12}},{"name":"Alt-Fire","speed":1,"crit_chance":40,"crit_mult":2.2,"status_chance":10,"shot_type":"Projectile","trigger":"Auto Charge","damage":{"cold":800,"impact":600},"falloff":{"start":9,"end":18,"reduction":0.6657}}],"damage":{"cold":16,"impact":8,"puncture":22,"slash":12},"imageName":"https://img.arsenyx.com/RailjackRifle-361ad06e.png","compatTags":["PROJECTILE","ASSAULT_AMMO"]}