{"uniqueName":"/Lotus/Weapons/Infested/LongGuns/InfestedRifle","name":"Synapse","displayClass":"Rifle","modPools":["Rifle","Synapse","Rifle (No Aoe)"],"polarities":[],"exilusPolarity":"madurai","stancePolarity":null,"family":"Synapse","slot":"Primary","traits":["Infested"],"masteryReq":11,"productCategory":"LongGuns","fireRate":12.000001,"magazineSize":70,"reloadTime":1.5,"totalDamage":20,"damagePerShot":[0,0,0,0,0,0,0,0,0,0,0,0,20,0,0,0,0,0,0,0],"criticalChance":0.38999999,"criticalMultiplier":2.7,"procChance":0.13,"accuracy":100,"multishot":1,"trigger":"HELD","attacks":[{"name":"Normal Attack","speed":12,"crit_chance":39,"crit_mult":2.7,"status_chance":13,"shot_type":"Hit-Scan","range":27,"damage":{"corrosive":20}}],"damage":{"corrosive":20},"imageName":"https://img.arsenyx.com/Synapse-f0058dce.png","compatTags":["BEAM","ASSAULT_AMMO"]}