{"uniqueName":"/Lotus/Weapons/Tenno/Melee/Polearms/Naginata/ShrineMaidenNaginataWeapon","name":"Amanata","displayClass":"Polearm","modPools":["Melee","Polearms","Amanata"],"polarities":["madurai"],"exilusPolarity":null,"stancePolarity":"naramon","family":"Amanata","slot":"Melee","traits":["Tenno"],"masteryReq":2,"productCategory":"Melee","fireRate":1,"totalDamage":126,"damagePerShot":[0,37.800003,88.199997,0,0,0,0,0,0,0,0,0,0,0,0,0,0,0,0,0],"criticalChance":0.23999999,"criticalMultiplier":2,"procChance":0.24000001,"attacks":[{"name":"Normal Attack","speed":1,"crit_chance":24,"crit_mult":2,"status_chance":24,"damage":{"puncture":37.8,"slash":88.2}},{"name":"Slam Attack","speed":1,"crit_chance":24,"crit_mult":2,"status_chance":10,"shot_type":"AoE","range":7,"damage":{"blast":252},"falloff":{"start":0,"end":7,"reduction":0.5}},{"name":"Heavy Slam Attack","speed":1,"crit_chance":24,"crit_mult":2,"status_chance":10,"shot_type":"AoE","range":8,"damage":{"blast":378},"falloff":{"start":0,"end":8,"reduction":0.3}}],"damage":{"puncture":37.8,"slash":88.2},"imageName":"https://content.warframe.com/PublicExport/Lotus/Interface/Icons/StoreIcons/Weapons/MeleeWeapons/Weapons/NaginataWeapon.png!00_mczdTOg8AJcDwaaUyR-Riw"}