{"uniqueName":"/Lotus/Weapons/Tenno/Melee/Swords/PrimeKatana/PrimeNikana","name":"Nikana Prime","displayClass":"Nikana","modPools":["Melee","Nikanas","Nikana Prime"],"polarities":["madurai","vazarin"],"exilusPolarity":null,"stancePolarity":"madurai","family":"Nikana","slot":"Melee","traits":["Prime","Vaulted"],"masteryReq":12,"productCategory":"Melee","fireRate":1.0833334,"totalDamage":198,"damagePerShot":[9.9000006,9.9000006,178.2,0,0,0,0,0,0,0,0,0,0,0,0,0,0,0,0,0],"criticalChance":0.28,"criticalMultiplier":2.4000001,"procChance":0.27999997,"attacks":[{"name":"Normal Attack","speed":1.08,"crit_chance":28,"crit_mult":2.4,"status_chance":28,"damage":{"impact":9.9,"puncture":9.9,"slash":178.2}},{"name":"Slam Attack","speed":1.08,"crit_chance":28,"crit_mult":2.4,"status_chance":10,"shot_type":"AoE","range":6,"damage":{"impact":396},"falloff":{"start":0,"end":6,"reduction":0.5}},{"name":"Heavy Slam Attack","speed":1.08,"crit_chance":28,"crit_mult":2.4,"status_chance":10,"shot_type":"AoE","range":7,"damage":{"blast":594},"falloff":{"start":0,"end":7,"reduction":0.3}}],"damage":{"impact":9.9,"puncture":9.9,"slash":178.2},"imageName":"https://content.warframe.com/PublicExport/Lotus/Interface/Icons/StoreIcons/Weapons/MeleeWeapons/Weapons/NikanaPrime.png!00_hE2A4o4eHvlherKIii1D+g"}